snowblind/__init__.py
snowblind/_version.py
snowblind/jump_plus.py
snowblind/persist.py
snowblind/rc_selfcal.py
snowblind/snowblind.py
snowblind-0.2.1.dist-info/LICENSE
snowblind-0.2.1.dist-info/METADATA
snowblind-0.2.1.dist-info/WHEEL
snowblind-0.2.1.dist-info/entry_points.txt
snowblind-0.2.1.dist-info/top_level.txt
snowblind-0.2.1.dist-info/RECORD
