Metadata-Version: 2.1
Name: snowblind
Version: 0.2.1
Summary: Mask cosmic ray showers (snowballs) in JWST data
Author-email: James Davies <jdavies@mpia.de>
License: BSD 3-Clause License
Project-URL: Bug Tracker, https://github.com/mpi-astronomy/snowblind/issues
Project-URL: Source Code, https://github.com/mpi-astronomy/snowblind
Classifier: Programming Language :: Python :: 3
Classifier: License :: OSI Approved :: BSD License
Classifier: Operating System :: OS Independent
Requires-Python: >=3.9
License-File: LICENSE
Requires-Dist: jwst
Requires-Dist: numpy
Requires-Dist: scikit-image >=0.20.0
Requires-Dist: stpipe
Provides-Extra: docs
Requires-Dist: sphinx ; extra == 'docs'
Requires-Dist: sphinx-automodapi ; extra == 'docs'
Requires-Dist: numpydoc ; extra == 'docs'
Provides-Extra: test
Requires-Dist: pytest ; extra == 'test'
Requires-Dist: flake8 ; extra == 'test'
Requires-Dist: flake8-pyproject ; extra == 'test'
Requires-Dist: codecov ; extra == 'test'
Requires-Dist: pytest-cov ; extra == 'test'
